multi_mst/__init__.py
multi_mst/base.py
multi_mst/kmst.py
multi_mst/kmst_descent.py
multi_mst/ksmt_descent_recall.py
multi_mst/noisy_mst.py
multi_mst/lib/__init__.py
multi_mst/lib/boruvka.py
multi_mst/lib/branches.py
multi_mst/lib/descent.py
multi_mst/lib/descent_recall.py
multi_mst/lib/graph.py
multi_mst/lib/heap.py
multi_mst/lib/kdtree.py
multi_mst/lib/kdtree_noisy.py
multi_mst/tests/__init__.py
multi_mst/tests/test_descent.py
multi_mst/tests/test_kmst.py
multi_mst/tests/test_noisy_mst.py
multi_mst/tests/test_recall.py
multi_mst-0.2.0.dist-info/LICENSE
multi_mst-0.2.0.dist-info/METADATA
multi_mst-0.2.0.dist-info/WHEEL
multi_mst-0.2.0.dist-info/top_level.txt
multi_mst-0.2.0.dist-info/RECORD
